{
  "bcv": 499.86,
  "binance": {
    "compra": 651.22,
    "venta": 651.83,
    "promedio": 651.53
  },
  "warnings": {
    "bcv": null,
    "binance": null
  },
  "diagnostics": {
    "binance": {
      "compra": {
        "label": "Compra app",
        "binanceTradeType": "SELL",
        "tradeType": "SELL",
        "selectedBank": "Provincial",
        "selectedPayTypes": [
          "Provincial"
        ],
        "selectedMethod": "avg-highest-5-filtered",
        "selectedSource": "binance-p2p-SELL",
        "sourceRates": [
          {
            "source": "binance-p2p-SELL",
            "bankLabel": "Provincial",
            "payTypes": [
              "Provincial"
            ],
            "method": "avg-highest-5-filtered",
            "rate": 651.22,
            "sampleSize": 20,
            "rawSampleSize": 20,
            "samplePrices": [
              651.41,
              651.4,
              651.3,
              651,
              651
            ],
            "ignoredOutliers": []
          }
        ],
        "errors": []
      },
      "venta": {
        "label": "Venta app",
        "binanceTradeType": "BUY",
        "tradeType": "BUY",
        "selectedBank": "Provincial",
        "selectedPayTypes": [
          "Provincial"
        ],
        "selectedMethod": "avg-lowest-5-filtered",
        "selectedSource": "binance-p2p-BUY",
        "sourceRates": [
          {
            "source": "binance-p2p-BUY",
            "bankLabel": "Provincial",
            "payTypes": [
              "Provincial"
            ],
            "method": "avg-lowest-5-filtered",
            "rate": 651.83,
            "sampleSize": 19,
            "rawSampleSize": 20,
            "samplePrices": [
              651.5,
              651.75,
              651.89,
              652,
              652
            ],
            "ignoredOutliers": [
              640
            ]
          }
        ],
        "errors": []
      }
    }
  },
  "updatedAt": "2026-05-10T21:09:28.992Z"
}
